README.txt
setup.py
zhpy/__init__.py
zhpy/commandline.py
zhpy/import_hook.py
zhpy/info.py
zhpy/interpreter.py
zhpy/plugcn.py
zhpy/plugtw.py
zhpy/pyparsing.py
zhpy/pyzh.py
zhpy/release.py
zhpy/zhdc.py
zhpy/zhpy.py
zhpy.egg-info/PKG-INFO
zhpy.egg-info/SOURCES.txt
zhpy.egg-info/dependency_links.txt
zhpy.egg-info/entry_points.txt
zhpy.egg-info/not-zip-safe
zhpy.egg-info/requires.txt
zhpy.egg-info/top_level.txt
zhpy/ext/__init__.py
zhpy/ext/pygmentplugin.py