Metadata-Version: 1.1
Name: zhpy
Version: 1.7.4
Summary: 周蟒, Write python language in chinese
Home-page: https://github.com/gasolin/zhpy
Author: Fred Lin
Author-email: gasolin+zhpy@gmail.com
License: MIT <http://www.opensource.org/licenses/mit-license.php>
Download-URL: https://github.com/gasolin/zhpy
Keywords: traditional,simplified,chinese
Platform: UNKNOWN
Classifier: Development Status :: 5 - Production/Stable
Classifier: Environment :: Console
Classifier: Intended Audience :: Education
Classifier: Intended Audience :: Developers
Classifier: Intended Audience :: System Administrators
Classifier: License :: OSI Approved :: MIT License
Classifier: Natural Language :: Chinese (Traditional)
Classifier: Natural Language :: Chinese (Simplified)
Classifier: Operating System :: OS Independent
Classifier: Programming Language :: Python
Classifier: Topic :: Software Development :: Libraries :: Python Modules
Classifier: Topic :: Software Development :: Code Generators
